ihan/__init__.py
ihan-0.3.21.data/scripts/ihan
ihan-0.3.21.dist-info/LICENSE
ihan-0.3.21.dist-info/METADATA
ihan-0.3.21.dist-info/WHEEL
ihan-0.3.21.dist-info/top_level.txt
ihan-0.3.21.dist-info/RECORD
