Metadata-Version: 2.1
Name: ihan
Version: 0.3.21
Summary: IHAN Client for feeding and back filling log files
Home-page: https://www.ihan.ee/
Author: Mark Litwintschik
Author-email: mark@marksblogg.com
License: MIT
Project-URL: Bug Tracker, https://github.com/marklit/ihan/issues
Project-URL: Documentation, https://ihan.readthedocs.io/en/latest/
Project-URL: Source Code, https://github.com/marklit/ihan
Platform: UNKNOWN
Classifier: Development Status :: 3 - Alpha
Classifier: Environment :: Console
Classifier: Intended Audience :: Developers
Classifier: Intended Audience :: System Administrators
Classifier: License :: OSI Approved :: MIT License
Classifier: Operating System :: POSIX :: Linux
Classifier: Programming Language :: Python :: 2.6
Classifier: Programming Language :: Python :: 2.7
Classifier: Programming Language :: Python :: 3.4
Classifier: Programming Language :: Python :: 3.5
Classifier: Programming Language :: Python :: 3.6
Classifier: Topic :: System :: Networking :: Monitoring
Requires-Dist: Click
Requires-Dist: requests
